dwhgen/__init__.py
dwhgen/csv2parquet.py
dwhgen/dbtparse.py
dwhgen/dv.py
dwhgen/hub.json
dwhgen/main.py
dwhgen/meta.py
dwhgen/pbi.py
dwhgen/schema.json
dwhgen/template/common/template/exasol/initial/psa_initial.sql
dwhgen/template/common/template/exasol/initial/psa_insert.sql
dwhgen/template/common/template/exasol/interface/psa_interface.sql
dwhgen/template/common/templates/dbt/psa_insert.sql
dwhgen/template/common/templates/dbt/source.yml
dwhgen/template/common/templates/psa/psa.sql
dwhgen/template/common/templates/source_schema/source_schema.sql
dwhgen/template/common/templates_dbt/src/psa_src.sql
dwhgen/template/common/templates_dbt/stg/stg.sql
dwhgen/template/exasol/templates/dbt/psa_insert.sql
dwhgen/template/exasol/templates/dbt/seeds.yml
dwhgen/template/exasol/templates/dbt/source.yml
dwhgen/template/exasol/templates_dbt/stg/stg.sql
dwhgen/workspace.code-workspace
dwhgen-0.1.2.dist-info/entry_points.txt
dwhgen-0.1.2.dist-info/WHEEL
dwhgen-0.1.2.dist-info/METADATA
dwhgen-0.1.2.dist-info/RECORD
